shrijuu/__init__.py
shrijuu/core.py
shrijuu/exceptions.py
shrijuu/utils.py
tests/__init__.py
tests/test_core.py
shrijuu-0.1.0.dist-info/LICENSE
shrijuu-0.1.0.dist-info/METADATA
shrijuu-0.1.0.dist-info/WHEEL
shrijuu-0.1.0.dist-info/top_level.txt
shrijuu-0.1.0.dist-info/RECORD
