Metadata-Version: 2.2
Name: shrijuu
Version: 0.1.0
Summary: A fun Python module representing a girlfriend character with interactive features.
Home-page: https://github.com/harshitkumar9030/shrijuu
Author: Harshit Kumar
Author-email: harshitkumar9030@gmail.com
Classifier: Programming Language :: Python :: 3
Classifier: License :: OSI Approved :: MIT License
Classifier: Operating System :: OS Independent
Requires-Python: >=3.6
License-File: LICENSE
Dynamic: author
Dynamic: author-email
Dynamic: classifier
Dynamic: description
Dynamic: description-content-type
Dynamic: home-page
Dynamic: requires-python
Dynamic: summary
